<?xml version="1.0" encoding="utf-8"?>
<!--Voor validatie is het noodzakelijk om ook de catalogi van de gepubliceerde versie 1.0.4-rc te laden.-->
<AanleveringInformatieObject xmlns="https://standaarden.overheid.nl/lvbb/stop/aanlevering/"
                             xmlns:geo="https://standaarden.overheid.nl/stop/imop/geo/"
                             xmlns:xsi="http://www.w3.org/2001/XMLSchema-instance"
                             schemaversie="1.0.4-rc"
                             xsi:schemaLocation="https://standaarden.overheid.nl/lvbb/stop/aanlevering https://standaarden.overheid.nl/lvbb/1.0.4-rc/lvbb-stop-aanlevering.xsd">
   <InformatieObjectVersie>
      <ExpressionIdentificatie xmlns="https://standaarden.overheid.nl/stop/imop/data/">
         <FRBRWork>/join/id/regdata/pv26/2020/regionaalfietsnetwerk</FRBRWork>
         <FRBRExpression>/join/id/regdata/pv26/2020/regionaalfietsnetwerk/nld@2020-06-02</FRBRExpression>
         <soortWork>/join/id/stop/work_010</soortWork>
      </ExpressionIdentificatie>
      <InformatieObjectVersieMetadata xmlns="https://standaarden.overheid.nl/stop/imop/data/">
         <heeftGeboorteregeling>/akn/nl/act/pv26/2020/OVPU001</heeftGeboorteregeling>
         <heeftBestanden>
            <heeftBestand>
               <Bestand>
                  <bestandsnaam>Behoudregionaalfietsnetwerk.gml</bestandsnaam>
                  <hash>782f5797916fd5566ad9a2dd660932b84d7aa99a8c4b2e1ff4e3c001c8b08b4ccbf7fcef0f97dd1e5649d4c661a0b2b190ce6e156911b0b811f020ea9a606c86</hash>
               </Bestand>
            </heeftBestand>
         </heeftBestanden>
      </InformatieObjectVersieMetadata>
      <InformatieObjectMetadata xmlns="https://standaarden.overheid.nl/stop/imop/data/">
         <eindverantwoordelijke>/tooi/id/provincie/pv26</eindverantwoordelijke>
         <maker>/tooi/id/provincie/pv26</maker>
         <alternatieveTitels>
            <alternatieveTitel>Regionaal fietsnetwerk</alternatieveTitel>
         </alternatieveTitels>
         <officieleTitel>/join/id/regdata/pv26/2020/regionaalfietsnetwerk</officieleTitel>
         <publicatieinstructie>TeConsolideren</publicatieinstructie>
         <naamInformatieObject>Regionaal fietsnetwerk</naamInformatieObject>
         <formaatInformatieobject>/join/id/stop/informatieobject/gio_002</formaatInformatieobject>
      </InformatieObjectMetadata>
   </InformatieObjectVersie>
</AanleveringInformatieObject>
