<?xml version="1.0" encoding="utf-8"?>
<!--Voor validatie is het noodzakelijk om ook de catalogi van de gepubliceerde versie 1.0.4 te laden.-->
<AanleveringInformatieObject xmlns="https://standaarden.overheid.nl/lvbb/stop/aanlevering/"
                             xmlns:geo="https://standaarden.overheid.nl/stop/imop/geo/"
                             xmlns:xsi="http://www.w3.org/2001/XMLSchema-instance"
                             schemaversie="1.2.0"
                             xsi:schemaLocation="https://standaarden.overheid.nl/lvbb/stop/aanlevering https://standaarden.overheid.nl/lvbb/1.2.0/lvbb-stop-aanlevering.xsd">
   <InformatieObjectVersie>
      <ExpressionIdentificatie xmlns="https://standaarden.overheid.nl/stop/imop/data/">
         <FRBRWork>/join/id/regdata/pv26/2020/aandachtsgebiedstiltegebied</FRBRWork>
         <FRBRExpression>/join/id/regdata/pv26/2020/aandachtsgebiedstiltegebied/nld@2020-06-02</FRBRExpression>
         <soortWork>/join/id/stop/work_010</soortWork>
      </ExpressionIdentificatie>
      <InformatieObjectVersieMetadata xmlns="https://standaarden.overheid.nl/stop/imop/data/">
         <heeftGeboorteregeling>/akn/nl/act/pv26/2020/OVPU001</heeftGeboorteregeling>
         <heeftBestanden>
            <heeftBestand>
               <Bestand>
                  <bestandsnaam>AandachtsgebiedStiltegebied.gml</bestandsnaam>
                  <hash>f97bd53920797f6fffb9d613bfd661a4e4181458b6d3122bf5dee4f36b15183a377dc440e0fcbb3907b43f5890be6142a16ccfdfcc3c97d14650ce3f195c35c9</hash>
               </Bestand>
            </heeftBestand>
         </heeftBestanden>
      </InformatieObjectVersieMetadata>
      <InformatieObjectMetadata xmlns="https://standaarden.overheid.nl/stop/imop/data/">
         <eindverantwoordelijke>/tooi/id/provincie/pv26</eindverantwoordelijke>
         <maker>/tooi/id/provincie/pv26</maker>
         <alternatieveTitels>
            <alternatieveTitel>Aandachtsgebied stiltegebied</alternatieveTitel>
         </alternatieveTitels>
         <officieleTitel>/join/id/regdata/pv26/2020/aandachtsgebiedstiltegebied</officieleTitel>
         <publicatieinstructie>TeConsolideren</publicatieinstructie>
         <naamInformatieObject>Aandachtsgebied stiltegebied</naamInformatieObject>
         <formaatInformatieobject>/join/id/stop/informatieobject/gio_002</formaatInformatieobject>
      </InformatieObjectMetadata>
   </InformatieObjectVersie>
</AanleveringInformatieObject>
